universe_ai/__init__.py
universe_ai/client.py
universe_ai/config.py
universe_ai/model.py
universe_ai/models/__init__.py
universe_ai/models/claude/__init__.py
universe_ai/models/claude/client.py
universe_ai/models/claude/config.py
universe_ai/models/monica/__init__.py
universe_ai/models/monica/chat/__init__.py
universe_ai/models/monica/chat/base_model.py
universe_ai/models/monica/chat/model.py
universe_ai/models/monica/chat/monica_bot.py
universe_ai/models/monica/config.py
universe_ai-0.1.0.dist-info/WHEEL
universe_ai-0.1.0.dist-info/METADATA
universe_ai-0.1.0.dist-info/RECORD
